{
    "policyId": null,
    "proposerId": null,
    "risk": {
        "affinity": "SCAR",
        "channelCode": "",
        "schemeCode": "",
        "optionalExtras": null,
        "extraDuqs": null,
        "product": {
            "vehicle": {
                "vehicleDetail": [
                    {
                        "vrn": "LK66WBX",
                        "abiCode": "90300263",
                        "productionPeriod": "2014-2017",
                        "yearOfManufacture": "2016",
                        "engineCc": "1984",
                        "engineGroup": "",
                        "fuelType": "P",
                        "manufacturer": "VOLKSWAGEN",
                        "model": "GOLF R TSI",
                        "bodyStyle": "H",
                        "seats": "2",
                        "transmissionType": "A",
                        "handednessDrivingType": "LeftHand",
                        "datePurchased": "2021-12-17",
                        "owner": "Proposer",
                        "registeredKeeper": true,
                        "locationParkedOvernight": "D",
                        "postcodeParkedOvernight": null,
                        "parkOvernightAtHome": true,
                        "classOfUse": "SDPexC",
                        "mileage": [
                            {
                                "type": "Total",
                                "value": "2999"
                            }
                        ],
                        "currentValue": "1234",
                        "purchasePrice": "1234",
                        "mainDriverId": 2,
                        "securityDevices": [
                            {
                                "type": "Immobiliser",
                                "code": "1317"
                            },
                            {
                                "type": "Tracking",
                                "code": "NONE"
                            },
                            {
                                "type": "alarm",
                                "code": "FACT"
                            }
                        ],
                        "isModified": false,
                        "abs": null,
                        "notBoughtYet": true,
                        "numberOfDoors": "5",
                        "locationParkedDaily": "HOME",
                        "goodsVehicle": {
                            "radiusLimit": "100",
                            "grossWeight": 2.94,
                            "HazardousGoods": false,
                            "SignWriting": false,
                            "Racking": false,
                            "Refrigerated": false
                        },
                        "coverType": "C"
                    }
                ],
                "additionalDrivers": [
                    {
                        "PublicLiability": true,
                        "additionalDrivingExperience": [],
                        "address": null,
                        "clientCategory": null,
                        "clientStatus": null,
                        "dateOfBirth": "1970-02-01",
                        "driverType": null,
                        "drivingLicence": [
                            {
                                "type": "F",
                                "typeOf": "Vehicle",
                                "dateObtained": "2015-02-01",
                                "cbtObtained": null,
                                "holdCbtCertificate": null
                            }
                        ],
                        "emailAddress": null,
                        "employment": [
                            {
                                "type": "fulltime",
                                "employmentCode": "E",
                                "employmentDesc": null,
                                "occupationCode": "02A",
                                "employerCode": "189",
                                "employerDesc": null
                            }
                        ],
                        "forenames": "Viet",
                        "fsaClass": null,
                        "gender": "M",
                        "homeOwner": null,
                        "iamCert": null,
                        "id": 2,
                        "insureOtherVehicle": null,
                        "largestNcbInOtherVehicle": "",
                        "maritalStatus": "M",
                        "medicalConditions": [
                            {
                                "type": "GLAR",
                                "date": "1970-01-01",
                                "notifiedDvla": false,
                                "restrictionDvla": true,
                                "claims": "1",
                                "status": "STABLE",
                                "vehicleModified": false,
                                "treatment": false,
                                "treatmentDescription": null,
                                "insulinInjections": null,
                                "insulinUnits": null,
                                "coronaryAttacks": null,
                                "coronaryByPass": false,
                                "coronaryDate": "1/1/0001"
                            }
                        ],
                        "membership": null,
                        "ncb": {
                            "otherBikeEngineCc": null,
                            "otherBikeLastRide": null,
                            "otherBikeNcd": null,
                            "otherBikeOwnership": null,
                            "otherBikeStyle": null,
                            "otherBikeYearOfManufacture": null,
                            "ownOtherBike": false,
                            "protectedBonus": null,
                            "previousNCBProtected": false,
                            "years": null,
                            "appliedToOtherVehicle": false,
                            "bonusProofType": null
                        },
                        "nonRTAConviction": null,
                        "otherVehicleUse": "NAOV",
                        "phoneNumbers": [],
                        "preferences": [],
                        "previousInsurance": {
                            "type": null,
                            "expiryDate": "2020-05-26T00:00:00",
                            "yearsHeld": null,
                            "insurerCode": null,
                            "insurerName": null,
                            "policyNumber": null
                        },
                        "relationshipToProposer": "S",
                        "salutation": "Mr Beo",
                        "smoker": null,
                        "starRider": null,
                        "suffix": null,
                        "surname": "Beo",
                        "tests": "",
                        "title": "Mr",
                        "ukResidentSinceDate": "1970-02-01",
                        "vatRegistered": null
                    }
                ]
            },
            "policyStartDate": "<<PolicyStartDate>>",
            "voluntaryExcess": "250",
            "claims": [
                {
                    "id": 1,
                    "personId": 1,
                    "code": "S003",
                    "date": "2017-02-01",
                    "ncbAffected": false,
                    "costs": "1",
                    "personalInjury": false,
                    "thisPolicy": true,
                    "thirdPartyCost": null,
                    "comments": null,
                    "brokerReference": null
                }
            ],
            "convictions": [
                {
                    "id": 1,
                    "personId": 2,
                    "type": null,
                    "code": "AC30",
                    "date": "2017-03-02",
                    "banLength": "0",
                    "fineAmount": "0",
                    "penaltyPoints": "1",
                    "drinkReading": null,
                    "drinkReadingLevel": null,
                    "relatedAccident": null,
                    "offenceDate": "2017-03-02"
                }
            ],
            "numberOfVehiclesInHousehold": "2",
            "insuranceRefused": false,
            "howDoYouPayForInsurance": "F",
            "notHadPreviousInsurance": false,
            "preferredPaymentMethod": null
        },
        "proposer": {
            "PublicLiability": true,
            "additionalDrivingExperience": [],
            "address": {
                "addressLine1": "11 Albert Street",
                "addressLine2": "STOKE-ON-TRENT",
                "addressLine3": "",
                "addressLine4": "",
                "addressLine5": "",
                "postCode": "ST3 5ED",
                "abodeType": "",
                "usage": "Main",
                "countryCode": "GB",
                "houseNameOrNumber": ""
            },
            "clientCategory": null,
            "clientStatus": null,
            "dateOfBirth": "1980-02-01",
            "driverType": null,
            "drivingLicence": [
                {
                    "type": "F",
                    "typeOf": "Vehicle",
                    "dateObtained": "2015-02-01",
                    "cbtObtained": null,
                    "holdCbtCertificate": null
                }
            ],
            "emailAddress": "nashtech.atlanta@outlook.com",
            "employment": [
                {
                    "type": "fulltime",
                    "employmentCode": "E",
                    "employmentDesc": null,
                    "occupationCode": "01A",
                    "employerCode": "001",
                    "employerDesc": null
                }
            ],
            "forenames": "Hoan",
            "fsaClass": null,
            "gender": "F",
            "homeOwner": true,
            "iamCert": null,
            "id": 1,
            "maritalStatus": "M",
            "medicalConditions": [
                {
                    "type": "GLAR",
                    "date": "1970-01-01",
                    "notifiedDvla": false,
                    "restrictionDvla": true,
                    "claims": "1",
                    "status": "STABLE",
                    "vehicleModified": false,
                    "treatment": false,
                    "treatmentDescription": null,
                    "insulinInjections": null,
                    "insulinUnits": null,
                    "coronaryAttacks": null,
                    "coronaryByPass": false,
                    "coronaryDate": "1/1/0001"
                }
            ],
            "membership": [],
            "ncb": {
                "otherBikeEngineCc": null,
                "otherBikeLastRide": null,
                "otherBikeNcd": null,
                "otherBikeOwnership": null,
                "otherBikeStyle": null,
                "otherBikeYearOfManufacture": null,
                "ownOtherBike": false,
                "protectedBonus": null,
                "previousNCBProtected": false,
                "years": "8",
                "appliedToOtherVehicle": false,
                "bonusProofType": null
            },
            "nonRTAConviction": null,
            "phoneNumbers": [
                {
                    "type": "Work",
                    "number": "07325345345435",
                    "id": null,
                    "extension": ""
                }
            ],
            "preferences": [
                {
                    "type": "Marketing",
                    "subType": "Post",
                    "code": null,
                    "value": "No",
                    "displaySubType": "Post",
                    "order": 1
                },
                {
                    "type": "Marketing",
                    "subType": "Email",
                    "code": null,
                    "value": "No",
                    "displaySubType": "Email",
                    "order": 2
                },
                {
                    "type": "Marketing",
                    "subType": "Tel",
                    "code": null,
                    "value": "No",
                    "displaySubType": "Phone",
                    "order": 3
                },
                {
                    "type": "Marketing",
                    "subType": "SMS",
                    "code": null,
                    "value": "No",
                    "displaySubType": "SMS",
                    "order": 4
                },
                {
                    "type": "Marketing",
                    "subType": "ArdonaghGroupMarketing",
                    "code": null,
                    "value": "N",
                    "order": 5
                }
            ],
            "previousInsurance": {
                "type": null,
                "expiryDate": "2020-05-26T00:00:00",
                "yearsHeld": null,
                "insurerCode": null,
                "insurerName": null,
                "policyNumber": null
            },
            "relationshipToProposer": null,
            "salutation": "Miss Trinh",
            "smoker": null,
            "starRider": null,
            "suffix": null,
            "surname": "Trinh",
            "tests": "",
            "title": "Miss",
            "ukResidentSinceDate": "1980-02-01",
            "vatRegistered": null,
            "otherVehicleUse": "OOC",
            "insureOtherVehicle": true,
            "largestNcbInOtherVehicle": "7"
        },
        "sourceOfSale": "",
        "webReference": null
    },
    "providerCodeList": null
}